LICENSE
README.md
esque/.python-version
esque/__init__.py
esque/__main__.py
esque/cli/__init__.py
esque/cli/autocomplete.py
esque/cli/commands/__init__.py
esque/cli/commands/apply.py
esque/cli/commands/config/__init__.py
esque/cli/commands/config/autocomplete.py
esque/cli/commands/config/edit.py
esque/cli/commands/config/fix.py
esque/cli/commands/config/migrate.py
esque/cli/commands/config/recreate.py
esque/cli/commands/consume.py
esque/cli/commands/create/__init__.py
esque/cli/commands/create/consumergroup.py
esque/cli/commands/create/topic.py
esque/cli/commands/ctx.py
esque/cli/commands/delete/__init__.py
esque/cli/commands/delete/consumergroup.py
esque/cli/commands/delete/topic.py
esque/cli/commands/delete/topics.py
esque/cli/commands/describe/__init__.py
esque/cli/commands/describe/broker.py
esque/cli/commands/describe/consumergroup.py
esque/cli/commands/describe/topic.py
esque/cli/commands/edit/__init__.py
esque/cli/commands/edit/offsets.py
esque/cli/commands/edit/topic.py
esque/cli/commands/get/__init__.py
esque/cli/commands/get/brokers.py
esque/cli/commands/get/consumergroups.py
esque/cli/commands/get/offset.py
esque/cli/commands/get/timestamp.py
esque/cli/commands/get/topics.py
esque/cli/commands/get/watermarks.py
esque/cli/commands/io.py
esque/cli/commands/ping.py
esque/cli/commands/produce.py
esque/cli/commands/set_/__init__.py
esque/cli/commands/set_/offsets.py
esque/cli/commands/transfer.py
esque/cli/commands/urlencode.py
esque/cli/environment.py
esque/cli/helpers.py
esque/cli/options.py
esque/cli/output.py
esque/cluster.py
esque/config/__init__.py
esque/config/migration.py
esque/config/sample_config.yaml
esque/controller/__init__.py
esque/controller/consumergroup_controller.py
esque/controller/topic_controller.py
esque/errors.py
esque/helpers.py
esque/io/__init__.py
esque/io/data_types.py
esque/io/exceptions.py
esque/io/handlers/__init__.py
esque/io/handlers/base.py
esque/io/handlers/kafka.py
esque/io/handlers/path.py
esque/io/handlers/pipe.py
esque-0.6.0.dist-info/LICENSE
esque-0.6.0.dist-info/METADATA
esque-0.6.0.dist-info/WHEEL
esque-0.6.0.dist-info/entry_points.txt
esque-0.6.0.dist-info/RECORD
