Metadata-Version: 2.1
Name: esque
Version: 0.6.0
Summary: esque - an operational kafka tool.
Home-page: https://github.com/real-digital/esque
License: MIT
Keywords: kafka,cli,commandline,administration,operation
Author: real.digital
Author-email: opensource@real-digital.de
Requires-Python: >=3.8,<3.11
Classifier: Development Status :: 4 - Beta
Classifier: Intended Audience :: Developers
Classifier: Intended Audience :: System Administrators
Classifier: License :: OSI Approved :: MIT License
Classifier: Programming Language :: Python :: 3
Classifier: Programming Language :: Python :: 3.8
Classifier: Programming Language :: Python :: 3.9
Classifier: Programming Language :: Python :: 3.10
Classifier: Topic :: Software Development
Classifier: Topic :: System :: Systems Administration
Requires-Dist: avro-python3 (>=1.9,<2.0)
Requires-Dist: click (==8.1.3)
Requires-Dist: confluent-kafka[avro] (>=1.6,<2.0)
Requires-Dist: fastavro (>=1.0,<2.0)
Requires-Dist: kafka-python (>=2.0.2,<3.0.0)
Requires-Dist: more-itertools (>=8.10.0,<9.0.0)
Requires-Dist: pendulum (>=2.0,<3.0)
Requires-Dist: pyyaml (==6.0.1)
Requires-Dist: requests (>=2.22,<3.0)
Requires-Dist: toml (>=0.10.0,<0.11.0)
Requires-Dist: yamale (>=2,<4)
Project-URL: Repository, https://github.com/real-digital/esque
